stabix/__init__.py
stabix/stabixcore.so
stabix-2.0.0.dist-info/METADATA
stabix-2.0.0.dist-info/WHEEL
stabix-2.0.0.dist-info/top_level.txt
stabix-2.0.0.dist-info/RECORD
