Metadata-Version: 2.4
Name: stabix
Version: 2.0.0
Summary: S(tatistical)tabix
Author: Kristen Schneider, Simon Walker
Maintainer-email: Simon Walker <simon@simonwalker.tech>
Project-URL: repository, https://github.com/kristen-schneider/stabix
Project-URL: paper, https://www.biorxiv.org/content/10.1101/2024.11.15.623812v1
Keywords: genomics,compression,bioinformatics,tabix,bed,gwas,genomics
Requires-Python: >=3.11
